port_eye/__init__.py
port_eye/export.py
port_eye/main.py
port_eye/mock_nmap.py
port_eye/report.py
port_eye/scanner.py
port_eye/utils.py
port_eye/templates/__init__.py
port_eye/templates/export.html.j2
port_eye/templates/style.css
port_eye-0.2.1.dist-info/LICENSE
port_eye-0.2.1.dist-info/METADATA
port_eye-0.2.1.dist-info/WHEEL
port_eye-0.2.1.dist-info/entry_points.txt
port_eye-0.2.1.dist-info/top_level.txt
port_eye-0.2.1.dist-info/RECORD
