Metadata-Version: 2.1
Name: port-eye
Version: 0.2.1
Summary: Simple CLI port scanner
Home-page: https://github.com/aHugues/port-eye.git
Author: Aurélien Hugues
Author-email: me@aurelienhugues.com
License: MIT
Platform: UNKNOWN
Classifier: Development Status :: 3 - Alpha
Classifier: Intended Audience :: Developers
Classifier: License :: OSI Approved :: MIT License
Classifier: Operating System :: OS Independent
Classifier: Programming Language :: Python
Classifier: Programming Language :: Python :: 2
Classifier: Programming Language :: Python :: 2.7
Classifier: Programming Language :: Python :: 3
Classifier: Programming Language :: Python :: 3.5
Classifier: Programming Language :: Python :: 3.6
Classifier: Programming Language :: Python :: 3.7
Requires-Python: >=2.7
Requires-Dist: click (>=7)
Requires-Dist: python-nmap (>=0.6)
Requires-Dist: jinja2 (>=2.10)
Requires-Dist: blessings (>=0.7)
Requires-Dist: pyfiglet (>=0.8)
Provides-Extra: dev
Requires-Dist: pytest ; extra == 'dev'
Requires-Dist: pytest-cov ; extra == 'dev'
Requires-Dist: codecov ; extra == 'dev'
Requires-Dist: black ; extra == 'dev'
Requires-Dist: pylint ; extra == 'dev'
Provides-Extra: test
Requires-Dist: pytest ; extra == 'test'
Requires-Dist: pytest-cov ; extra == 'test'
Requires-Dist: codecov ; extra == 'test'
